pyquadtree/__init__.py
pyquadtree/node.py
pyquadtree/quadtree.py
e_pyquadtree-0.1.1.dist-info/LICENSE
e_pyquadtree-0.1.1.dist-info/METADATA
e_pyquadtree-0.1.1.dist-info/WHEEL
e_pyquadtree-0.1.1.dist-info/top_level.txt
e_pyquadtree-0.1.1.dist-info/RECORD
