Metadata-Version: 2.1
Name: e_pyquadtree
Version: 0.1.1
Home-page: 
Author: Ethan Anderson
Author-email: telan4892@gmail.com
License-File: LICENSE
